{"date":"Sat, 06 Jun 2015 23:04:51 GMT","name":"http://vision.princeton.edu/data/dataset/shared/SUNRGBD/kv1/NYUdata/NYU0658/annotation2D3D/index.json","frames":[{"polygon":[{"x":[300,300,561.1863075196409,561.1863075196409],"y":[18.690235690235692,427,427,18.690235690235692],"object":0,"rect":1,"annotator":"112.95.200.117"}]}],"objects":[{"name":"shelf","polygon":[{"Ymin":0.8062499857,"Ymax":-0.2437499957,"rectangle":1,"X":[0.5359290336,0.5312481516,0.8933744135,0.8980552956],"Z":[0.837796647,0.3249988634,0.3216933299,0.8344911135]}]}],"imageNum":"658_bathroom_0012_3.mat","extrinsics":"20131231164405.txt","conflictList":[],"fileList":["http://vision.princeton.edu/data/dataset/shared/SUNRGBD/kv1/NYUdata/NYU0658/image/NYU0658.jpg"]}